napari_toska/ToskaSkeleton.py
napari_toska/__init__.py
napari_toska/_backend_toska_functions.py
napari_toska/_labeled_skeletonization.py
napari_toska/_measurements.py
napari_toska/_network_analysis.py
napari_toska/_utils.py
napari_toska/_version.py
napari_toska/_widget.py
napari_toska/napari.yaml
napari_toska/_tests/__init__.py
napari_toska/_tests/test_adjancency_matrix.py
napari_toska/_tests/test_skeletons.py
napari_toska-0.2.2.dist-info/licenses/LICENSE
napari_toska-0.2.2.dist-info/METADATA
napari_toska-0.2.2.dist-info/WHEEL
napari_toska-0.2.2.dist-info/entry_points.txt
napari_toska-0.2.2.dist-info/top_level.txt
napari_toska-0.2.2.dist-info/RECORD
