Metadata-Version: 2.4
Name: napari-toska
Version: 0.2.2
Summary: Extracts and analyses topological skeletons as undirected graphs
Author-email: Allyson Quinn Ryan <allyson_quinn.ryan@tu-dresden.de>, Johannes Soltwedel <johannes_richard.soltwedel@tu-dresden.de>
License: 
Project-URL: Bug Tracker, https://github.com/allysonryan/napari-toska/issues
Project-URL: Documentation, https://github.com/allysonryan/napari-toska
Project-URL: Source Code, https://github.com/allysonryan/napari-toska
Project-URL: User Support, https://github.com/allysonryan/napari-toska/issues
Keywords: network-analysis,skeletons,napari,napari-plugin
Classifier: Development Status :: 2 - Pre-Alpha
Classifier: Framework :: napari
Classifier: Intended Audience :: Developers
Classifier: License :: OSI Approved :: BSD License
Classifier: Operating System :: OS Independent
Classifier: Programming Language :: Python
Classifier: Programming Language :: Python :: 3
Classifier: Programming Language :: Python :: 3 :: Only
Classifier: Programming Language :: Python :: 3.9
Classifier: Programming Language :: Python :: 3.10
Classifier: Programming Language :: Python :: 3.11
Classifier: Programming Language :: Python :: 3.12
Classifier: Programming Language :: Python :: 3.13
Classifier: Topic :: Scientific/Engineering :: Image Processing
Requires-Python: >=3.9
License-File: LICENSE
Requires-Dist: numpy
Requires-Dist: magicgui
Requires-Dist: qtpy
Requires-Dist: scikit-image>=0.21.0
Requires-Dist: napari-skimage-regionprops
Requires-Dist: networkx
Requires-Dist: scipy
Requires-Dist: magicgui>=0.4.0
Requires-Dist: tqdm>=4.65.0
Provides-Extra: testing
Requires-Dist: tox; extra == "testing"
Requires-Dist: pytest; extra == "testing"
Requires-Dist: pytest-cov; extra == "testing"
Requires-Dist: pytest-qt; extra == "testing"
Requires-Dist: napari; extra == "testing"
Requires-Dist: pyqt5; extra == "testing"
Dynamic: license-file
